BlueMapWrapper/Collections.py
BlueMapWrapper/KEYS.py
BlueMapWrapper/MarkerSet.py
BlueMapWrapper/__init__.py
BlueMapWrapper/exceptions.py
BlueMapWrapper/player.py
BlueMapWrapper/positioning.py
BlueMapWrapper/settings.py
BlueMapWrapper/clients/AsyncClient.py
BlueMapWrapper/clients/Client.py
BlueMapWrapper/clients/__init__.py
BlueMapWrapper/markers/BaseMarker.py
BlueMapWrapper/markers/ExtrudeMarker.py
BlueMapWrapper/markers/HTMLMarker.py
BlueMapWrapper/markers/LineMarker.py
BlueMapWrapper/markers/POIMarker.py
BlueMapWrapper/markers/ShapeMarker.py
BlueMapWrapper/markers/__init__.py
BlueMapWrapper/markers/markers.py
BlueMapWrapper/plugins/Lands.py
BlueMapWrapper/plugins/__init__.py
bluemapwrapper-1.0.4.dist-info/licenses/LICENSE
unused/__init__.py
unused/map.py
bluemapwrapper-1.0.4.dist-info/METADATA
bluemapwrapper-1.0.4.dist-info/WHEEL
bluemapwrapper-1.0.4.dist-info/top_level.txt
bluemapwrapper-1.0.4.dist-info/RECORD
