Metadata-Version: 2.4
Name: BlueMapWrapper
Version: 1.0.4
Summary: A BlueMap Wrapper to get data from a BlueMap Map
Author-email: RyanStudio <ryanstudiobusiness@gmail.com>
License-Expression: MIT
Project-URL: Homepage, https://github.com/RyanStudioo/BlueMapMarkersWrapper
Project-URL: Issues, https://github.com/RyanStudioo/BlueMapMarkersWrapper/issues
Keywords: BlueMap,BlueMapWrapper,BlueMapWrapper.py
Classifier: Programming Language :: Python :: 3.13
Classifier: Operating System :: OS Independent
Requires-Python: >=3.9
License-File: LICENSE
Requires-Dist: requests>=2.0.0
Requires-Dist: aiohttp>=3.0.0
Dynamic: license-file
